{
  "settings": {
    "CUSTOM_REGEXPS": {
      "Basic": "((?:[^\\n][\\n]?)+) #flashcard ?\\n*((?:\\n(?:^.{1,3}$|^.{4}(?<!<!--).*))+)",
      "Basic (and reversed card)": "",
      "Basic (optional reversed card)": "",
      "Basic (type in the answer)": "",
      "CGW-InvalidExample": "",
      "CGW-ValidExample": "",
      "Chinese Grammar Wiki": "",
      "Cloze": "",
      "Tactic": ""
    },
    "FILE_LINK_FIELDS": {
      "Basic": "Front",
      "Basic (and reversed card)": "Front",
      "Basic (optional reversed card)": "Front",
      "Basic (type in the answer)": "Front",
      "CGW-InvalidExample": "中文",
      "CGW-ValidExample": "中文",
      "Chinese Grammar Wiki": "中文",
      "Cloze": "Text",
      "Tactic": "ID"
    },
    "CONTEXT_FIELDS": {},
    "FOLDER_DECKS": {
      "assets": "",
      "Neural Networks": "",
      "lists": "",
      "Assignments": "",
      "Excalidraw": "",
      "files": ""
    },
    "FOLDER_TAGS": {
      "assets": "",
      "Neural Networks": "",
      "lists": "",
      "Assignments": "",
      "Excalidraw": "",
      "files": ""
    },
    "Syntax": {
      "Begin Note": "START",
      "End Note": "END",
      "Begin Inline Note": "STARTI",
      "End Inline Note": "ENDI",
      "Target Deck Line": "TARGET DECK",
      "File Tags Line": "FILE TAGS",
      "Delete Note Line": "DELETE",
      "Frozen Fields Line": "FROZEN"
    },
    "Defaults": {
      "Tag": "Obsidian_to_Anki",
      "Deck": "Default",
      "Scheduling Interval": 0,
      "Add File Link": false,
      "Add Context": false,
      "CurlyCloze": false,
      "CurlyCloze - Highlights to Clozes": false,
      "ID Comments": true,
      "Add Obsidian Tags": false
    }
  },
  "Added Media": [
    "Pasted image 20220126133518.png",
    "Pasted image 20220126133539.png",
    "Pasted image 20220126133559.png",
    "Pasted image 20220126133102.png",
    "Pasted image 20220126133023.png",
    "Pasted image 20220126132746.png",
    "Pasted image 20220126132353.png",
    "Pasted image 20220126132428.png",
    "Pasted image 20220126132512.png",
    "Pasted image 20220330164443.png",
    "Pasted image 20220330164841.png",
    "Pasted image 20220330165307.png",
    "Pasted image 20220330172101.png",
    "Pasted image 20220330172126.png",
    "Pasted image 20220330172254.png"
  ],
  "File Hashes": {
    "Vectors.md": "f2b19284e05236e25ef7b85340d5bd4e",
    "Theorems.md": "ec10dd5801659ce276af3fec22e03924",
    "Sets.md": "13411667dc250df6e7357a009a52b287",
    "Planes.md": "e24c1aa08cb23cb3f402b21d78afd734",
    "Math Cheatsheet.md": "071d8e5792cfe54c643a9faad7a42f01",
    "hello.md": "9e46c05cc10c0aea6fb9e924ab7725c8",
    "test.md": "d41d8cd98f00b204e9800998ecf8427e",
    "Types of machine learning.md": "0094da920273cdeaf6ee6a3a63a39b8d",
    "Supervised Learning.md": "da50f56b432b84dd7b13ebd87e7b0006",
    "Reinforcement Learning.md": "b0238210d1ce5934ddb87f946a9b5e77",
    "Neural Networks/Neural Network Overview.md": "95fe9359fe8a03cd195d4a19e4f08761",
    "Neural Networks/Activation Functions.md": "d41d8cd98f00b204e9800998ecf8427e",
    "Markov Decision Process.md": "db558aae2f8c06cf4118ca2fd5dbc5d6",
    "Definitions/Discrete Math Cheatsheet.md": "ec10dd5801659ce276af3fec22e03924",
    "Definitions/Definitions.md": "df4e8d47efb8ceb616165c4880c60c8b",
    "Intro.md": "c8b279fbaaf8a59123c87d08866349cf",
    "Electric Charges and Forces.md": "d41d8cd98f00b204e9800998ecf8427e",
    "115 Sets.md": "6f9cd6b9a74c1498e57cfe6b70cc939e",
    "111 Planes.md": "e24c1aa08cb23cb3f402b21d78afd734",
    "110 Vectors.md": "957016379c7c5991a1cf1452b644b58f",
    "253 Types of machine learning.md": "3d6a747c0a69417e6f08215b29f0c037",
    "252 Supervised Learning.md": "7d0bd0672d863cf55fd09adbca1e5f9a",
    "251 Markov Decision Process.md": "db558aae2f8c06cf4118ca2fd5dbc5d6",
    "250 Reinforcement Learning.md": "3780dc9819123dbb784e57408a2fb834",
    "000 Index.md": "a3bc472c73ab93275152bc91a7a3a7b7",
    "lists/Math Cheatsheet.md": "071d8e5792cfe54c643a9faad7a42f01",
    "lists/Discrete Math Cheatsheet.md": "ec10dd5801659ce276af3fec22e03924",
    "lists/Definitions.md": "b1995847f02cb26b75c896dfc5872724",
    "116 Propositional Logic.md": "86737f320f49d896630823ea23d2d0dd",
    "Class monday 360.md": "b78c4120e22c8a2719619d9baf591f92",
    "351 Digital and Analog.md": "900e6f382216857a09413e9b027aab51",
    "400 Computer Science.md": "039bf04a377a81fd9f7d088e6fcf8907",
    "300 Physics.md": "d41d8cd98f00b204e9800998ecf8427e",
    "200 Statistics and Machine Learning.md": "d41d8cd98f00b204e9800998ecf8427e",
    "100 Math.md": "f69393a8eeba2a2827c282d859ee3321",
    "1 Me.md": "d41d8cd98f00b204e9800998ecf8427e",
    "451 Digital and Analog.md": "a8a01ad567aa2aa001d91522786a4d1d",
    "310 Electric Charges and Forces.md": "cea5e15bb9782d94eaa043d97bad3034",
    "11 Color Blind README.md": "ecc7fc45da38ee2494e8bb0598068655",
    "263 Hyper Parameters.md": "01e9ad92619ec743b4fecf5550af5af9",
    "262 Optimizers.md": "f5f243ca55b483922a5a8a077c76774f",
    "261 Backpropagation.md": "307643008ad7d494e64eaa619ba7ea4e",
    "260 Neural Networks.md": "57bbc1f0f168aa1c1b14b73c87dab0b8",
    "254 What is Deep Learning.md": "e493c75cc63a0fbd4a90e385edcd3424",
    "10 Best blogs.md": "81414ff70701cb865ec3a63230f5bef9",
    "Vector Functions.md": "70eafbe7d022606f9f096c298b6cb43d",
    "452 Computer Compontents.md": "15d753d0160f04fabdf1bbad5e53294b",
    "402 Tree Notes.md": "68e9e3a501c713d326f786f949955fb3",
    "401 Leetcode Tree Problems.md": "69b1633b74da8364dcde8e96a66acc73",
    "112 Vector Functions.md": "a18a52c50101e800e306f3bbe7f37080",
    "assets/Pasted image 20220127091704.md": "d41d8cd98f00b204e9800998ecf8427e",
    "Physics Midterm 2.md": "dabd3ffc1968566b372c03e37a1302df",
    "Magnetic Field.md": "01626e7e50d74fc6e00fd2c2cc5b41a4",
    "CMPSC 360 Midterm 2.md": "d44c7c1f2951766b2da2ea3f7efa3585",
    "453 Boolean Logic.md": "7b7f288ccdd9426995acbd53fbd16e82",
    "451 Number and Binary Representation.md": "55d2689cf483cde92a8f00bc05745e41",
    "312 Capacitor Problems.md": "481fea39d9d275bde35d1fe2138c69d4",
    "311 Gauss's Law.md": "9bb60348dd6c2109ec1338e16ce4a79d",
    "262 Loss Function and Optimizers.md": "3c3742c954631319df9d9e821b0419ae",
    "121 Number Theory and Cryptography.md": "7937a638c407139eeca1ab235e1cd3a4",
    "120 Sequences (Discrete Math).md": "d6f2e1760beaa95fad2d348968b23f34",
    "118 Relations and Functions.md": "ed07c19b419d1122507d0d23530651ee",
    "117 Proofs.md": "74d5ddaf02599898da1617ce94e2658a",
    "114 Multiple Integration.md": "3a6865d64a1050c0d130b934726e07e9",
    "113 Multivariable Functions.md": "82675aa4698ac92e0a24566288f3e7d0",
    "What is Deep Learning.md": "33d3ed71864553141d83e8d91642b8aa",
    "Types of data scientists.md": "dd9b5b355fb9208be49692b0127a2906",
    "Statistics & Machine Learning.md": "ed53985424f6197ec837830e1b35ea40",
    "Excalidraw/Drawing 2022-05-13 16.31.07.excalidraw.md": "8d9fbcd16508d2521f894ce62086a2ea",
    "Assignments/CMPSC 360 Midterm 2.md": "d44c7c1f2951766b2da2ea3f7efa3585",
    "Assignments/CMPSC 360 HW 9.md": "96dbf09415b412c3fc607ad06b2d524a",
    "Assignments/CMPSC 360 HW 7.md": "14923481ec7595db6a45d6d922dea861",
    "Machine Learning Specifications.md": "610ad507f631149ba7c16cfbc19732f3",
    "File Types.md": "a771f05cfb3cc67f78b5d69f41e7e883",
    "Leetcode.md": "a7d5791304587c173b8622f9f0c97d0e",
    "402 Sorting and Traversal Algorithms.md": "f879336ae4656d5eb4d8a4c3bf965bd4",
    "Contest Algoithms.md": "e82fb8ba653f4d1cc35d16bea17b2b37",
    "403 Designing Algorithms.md": "876ec77f42c55b1f753b1817d85c7141",
    "404 Data Structures.md": "1b0fc9b15736bde164481fd316f424fd",
    "80 Git.md": "3064c0d9f3512092db12a48a1a503cc9",
    "401 Big O.md": "bb2a63e0d701fc0c430154492aa31c1e",
    "271 Number and Binary Representation.md": "324700217e4892a699424e109f2caed3",
    "272 Computer Components.md": "b877d194784ed2695c7f964af251ad1a",
    "270 Computer Engineering.md": "fdfdb54133a52a7864ea04eb6cd13e05",
    "124 Fundamental Theorems of Vector Analysis.md": "700d56511cf4491555f31df81dd19d7d",
    "122 Counting and Probability.md": "740408847e9e0584b239f16c3e311b56",
    "123 Graphs and Trees.md": "2ddee055f1e0565aeedbf4a2db85c8b7",
    "119 Sets.md": "52838ad1a93f1c06ee77aa366e257cb8",
    "115 Line and Surface Integrals.md": "f205c7688fae3697ff428b18103ee3dd",
    "1004 Drake Train.md": "fcd9fa8467e099f7315d321cc5c3fe5f",
    "1003 Drake Val.md": "d41d8cd98f00b204e9800998ecf8427e",
    "1001 Drake.md": "829f152aad3137f95621c1d392166519",
    "1002 Drake old.md": "9e7bb45dcdca80b1aa06bb815294a2e4",
    "1000 late HTB.md": "58a63162cff476e587d80af3465bf15a",
    "0000 To Do.md": "a43335f1039b02aaf70eb35ae6987e4c"
  },
  "fields_dict": {
    "Basic": [
      "Front",
      "Back"
    ],
    "Basic (and reversed card)": [
      "Front",
      "Back"
    ],
    "Basic (optional reversed card)": [
      "Front",
      "Back",
      "Add Reverse"
    ],
    "Basic (type in the answer)": [
      "Front",
      "Back"
    ],
    "CGW-InvalidExample": [
      "中文",
      "Pinyin",
      "English",
      "Notes",
      "Example Type",
      "Article Title",
      "Grammar Construct",
      "Source URL"
    ],
    "CGW-ValidExample": [
      "中文",
      "Pinyin",
      "English",
      "Notes",
      "Example Type",
      "Article Title",
      "Grammar Construct",
      "Source URL"
    ],
    "Chinese Grammar Wiki": [
      "中文",
      "Pinyin",
      "English",
      "Notes",
      "Example Type",
      "Article Title",
      "Grammar Construct",
      "Source URL"
    ],
    "Cloze": [
      "Text",
      "Back Extra"
    ],
    "Tactic": [
      "ID",
      "FEN",
      "FlippedFEN",
      "Turn",
      "Solution1",
      "Solution2",
      "Motif"
    ]
  }
}